netseer/__init__.py
netseer/forecasting.py
netseer/generate_graph.py
netseer/netseer.py
netseer/prediction.py
netseer/py.typed
netseer/utils.py
netseer-0.1.1.dist-info/METADATA
netseer-0.1.1.dist-info/WHEEL
netseer-0.1.1.dist-info/entry_points.txt
netseer-0.1.1.dist-info/licenses/LICENSE
netseer-0.1.1.dist-info/RECORD
