Metadata-Version: 2.4
Name: netseer
Version: 0.1.1
Summary: Predicting graph structure from a time series of graphs
Project-URL: Homepage, https://github.com/sevvandi/netseer-python
Project-URL: Issues, https://github.com/sevvandi/netseer-python/issues
Project-URL: Documentation, https://sevvandi.github.io/netseer-python/
Author: Stefan Westerlund
Author-email: Brodie Oldfield <Brodie.Oldfield@gmail.com>
License-File: LICENSE
Requires-Python: >=3.12
Requires-Dist: igraph>=0.11.9
Requires-Dist: pulp>=3.2.1
Requires-Dist: statsforecast>=2.0.2
Requires-Dist: statsmodels>=0.14.5
